visionsdk/__init__.py
visionsdk/_events.py
visionsdk/custom_audio_track.py
visionsdk/custom_video_track.py
visionsdk/event_handler.py
visionsdk/exceptions.py
visionsdk/meeting.py
visionsdk/participant.py
visionsdk/pubsub.py
visionsdk/room_client.py
visionsdk/stream.py
visionsdk/utils.py
visionsdk/vision_sdk.py
visionsdk/lib/__init__.py
visionsdk/lib/pymediasoup/__init__.py
visionsdk/lib/pymediasoup/__version__.py
visionsdk/lib/pymediasoup/consumer.py
visionsdk/lib/pymediasoup/data_consumer.py
visionsdk/lib/pymediasoup/data_producer.py
visionsdk/lib/pymediasoup/device.py
visionsdk/lib/pymediasoup/emitter.py
visionsdk/lib/pymediasoup/errors.py
visionsdk/lib/pymediasoup/ortc.py
visionsdk/lib/pymediasoup/producer.py
visionsdk/lib/pymediasoup/rtp_parameters.py
visionsdk/lib/pymediasoup/scalability_modes.py
visionsdk/lib/pymediasoup/sctp_parameters.py
visionsdk/lib/pymediasoup/transport.py
visionsdk/lib/pymediasoup/handlers/__init__.py
visionsdk/lib/pymediasoup/handlers/aiortc_handler.py
visionsdk/lib/pymediasoup/handlers/handler_interface.py
visionsdk/lib/pymediasoup/handlers/sdp/__init__.py
visionsdk/lib/pymediasoup/handlers/sdp/common_utils.py
visionsdk/lib/pymediasoup/handlers/sdp/media_section.py
visionsdk/lib/pymediasoup/handlers/sdp/remote_sdp.py
visionsdk/lib/pymediasoup/handlers/sdp/unified_plan_utils.py
visionsdk/lib/pymediasoup/models/__init__.py
visionsdk/lib/pymediasoup/models/handler_interface.py
visionsdk/lib/pymediasoup/models/transport.py
visionsdk/worker/__init__.py
visionsdk/worker/character_state.py
visionsdk/worker/character_worker.py
visionsdk/worker/client.py
visionsdk/worker/schemas.py
visionsdk/worker/worker_service.py
visionsdk/worker/context/__init__.py
visionsdk/worker/context/character_context.py
visionsdk/worker/context/character_intent.py
visionsdk/worker/context/character_memory.py
visionsdk/worker/context/character_vision.py
visionsdk-0.0.2.dist-info/METADATA
visionsdk-0.0.2.dist-info/WHEEL
visionsdk-0.0.2.dist-info/top_level.txt
visionsdk-0.0.2.dist-info/RECORD
