Metadata-Version: 2.4
Name: visionsdk
Version: 0.0.2
Summary: VisionSDK Python SDK
Author: visionsdk
Author-email: sdk@neurarank.tech
License-Expression: MIT
Project-URL: Home, https://docs.neurarank.tech
Project-URL: Documentation, https://docs.neurarank.tech
Project-URL: Source, https://docs.neurarank.tech
Project-URL: Website, https://neurarank.tech
Keywords: ml,webrtc,audio,video,ai,visionsdk
Classifier: Development Status :: 3 - Alpha
Classifier: Intended Audience :: Developers
Classifier: Topic :: Communications :: Conferencing
Classifier: Topic :: Multimedia :: Sound/Audio
Classifier: Topic :: Scientific/Engineering :: Artificial Intelligence
Classifier: Programming Language :: Python :: 3.11
Requires-Python: >=3.11
Requires-Dist: pydantic>=1.10.15
Requires-Dist: vsaiortc>=0.0.6
Requires-Dist: h264-profile-level-id<1.1.0,>=1.0.0
Requires-Dist: sdp-transform<1.2.0,>=1.1.0
Requires-Dist: pyee>=13.0.0
Requires-Dist: av<17.0.0,>=14.0.0
Requires-Dist: websockets<=15.0.1,>=12.0.0
Requires-Dist: requests<2.32.0,>=2.3.1
Requires-Dist: pylibsrtp>=0.10.0
Requires-Dist: pyopenssl>=24.0.0
Requires-Dist: pycryptodome==3.20.0
Requires-Dist: pillow>=11.1.0
Dynamic: author-email
